covseisnet/__init__.py
covseisnet/arraystream.py
covseisnet/beam.py
covseisnet/correlationmatrix.py
covseisnet/covariancematrix.py
covseisnet/traveltime.py
covseisnet-1.0.0.dist-info/LICENSE
covseisnet-1.0.0.dist-info/METADATA
covseisnet-1.0.0.dist-info/WHEEL
covseisnet-1.0.0.dist-info/top_level.txt
covseisnet-1.0.0.dist-info/RECORD
